{
  "generated_utc": "2026-03-06T19:21:57.797020Z",
  "scraper": "apify",
  "batch": 3,
  "total_batches": 21,
  "companies_searched": 15,
  "total_jobs_found": 0,
  "eligible_jobs": 0,
  "itar_flagged": 0,
  "misconfigured_companies": [
    "Airbus",
    "Albany Engineered Composites",
    "Arconic",
    "Boeing",
    "Caterpillar",
    "Dover Corporation",
    "Ducommun",
    "DuPont",
    "Eaton"
  ],
  "scrape_diagnostics": [
    {
      "company": "ZeroAvia",
      "actor": "apify/cheerio-scraper",
      "stats": {
        "requests_total": 0,
        "requests_finished": 0,
        "items": 1,
        "diagnosis": "ok"
      }
    },
    {
      "company": "Form Energy",
      "actor": "apify/cheerio-scraper",
      "stats": {
        "requests_total": 0,
        "requests_finished": 0,
        "items": 1,
        "diagnosis": "ok"
      }
    },
    {
      "company": "QuantumScape",
      "actor": "apify/cheerio-scraper",
      "stats": {
        "requests_total": 0,
        "requests_finished": 0,
        "items": 1,
        "diagnosis": "ok"
      }
    },
    {
      "company": "Redwood Materials",
      "actor": "apify/cheerio-scraper",
      "stats": {
        "requests_total": 0,
        "requests_finished": 0,
        "items": 1,
        "diagnosis": "ok"
      }
    },
    {
      "company": "Airbus",
      "actor": "apify/puppeteer-scraper",
      "stats": {
        "requests_total": 0,
        "requests_finished": 0,
        "items": 0,
        "diagnosis": "likely_misconfiguration"
      }
    },
    {
      "company": "Albany Engineered Composites",
      "actor": "apify/puppeteer-scraper",
      "stats": {
        "requests_total": 0,
        "requests_finished": 0,
        "items": 0,
        "diagnosis": "likely_misconfiguration"
      }
    },
    {
      "company": "Arconic",
      "actor": "apify/puppeteer-scraper",
      "stats": {
        "requests_total": 0,
        "requests_finished": 0,
        "items": 0,
        "diagnosis": "likely_misconfiguration"
      }
    },
    {
      "company": "Boeing",
      "actor": "apify/puppeteer-scraper",
      "stats": {
        "requests_total": 0,
        "requests_finished": 0,
        "items": 0,
        "diagnosis": "likely_misconfiguration"
      }
    },
    {
      "company": "Caterpillar",
      "actor": "apify/puppeteer-scraper",
      "stats": {
        "requests_total": 0,
        "requests_finished": 0,
        "items": 0,
        "diagnosis": "likely_misconfiguration"
      }
    },
    {
      "company": "Collins Aerospace",
      "actor": "apify/puppeteer-scraper",
      "stats": {
        "requests_total": 0,
        "requests_finished": 0,
        "items": 1,
        "diagnosis": "ok"
      }
    },
    {
      "company": "Dover Corporation",
      "actor": "apify/puppeteer-scraper",
      "stats": {
        "requests_total": 0,
        "requests_finished": 0,
        "items": 0,
        "diagnosis": "likely_misconfiguration"
      }
    },
    {
      "company": "Ducommun",
      "actor": "apify/puppeteer-scraper",
      "stats": {
        "requests_total": 0,
        "requests_finished": 0,
        "items": 0,
        "diagnosis": "likely_misconfiguration"
      }
    },
    {
      "company": "DuPont",
      "actor": "apify/puppeteer-scraper",
      "stats": {
        "requests_total": 0,
        "requests_finished": 0,
        "items": 0,
        "diagnosis": "likely_misconfiguration"
      }
    },
    {
      "company": "Eaton",
      "actor": "apify/puppeteer-scraper",
      "stats": {
        "requests_total": 0,
        "requests_finished": 0,
        "items": 0,
        "diagnosis": "likely_misconfiguration"
      }
    },
    {
      "company": "GE Aerospace",
      "actor": "apify/puppeteer-scraper",
      "stats": {
        "requests_total": 0,
        "requests_finished": 0,
        "items": 1,
        "diagnosis": "ok"
      }
    }
  ],
  "jobs": []
}